vectorlogic/__init__.py
vectorlogic/engine.py
vectorlogic/helpers.py
vectorlogic/rule_converter.py
vectorlogic/rule_parser.py
vectorlogic/state_vector.py
vectorlogic/t_object.py
vector_logic-0.4.2.dist-info/METADATA
vector_logic-0.4.2.dist-info/WHEEL
vector_logic-0.4.2.dist-info/licenses/LICENSE
vector_logic-0.4.2.dist-info/RECORD
