Metadata-Version: 2.4
Name: vector-logic
Version: 0.4.2
Summary: A library for a simple rules engine.
License: MIT
License-File: LICENSE
Keywords: rules-engine,rules,business-rules,logic,state-vector,state-algebra
Author: Dmitry Lesnik
Author-email: dmitry@stratyfy.com
Requires-Python: >=3.9,<4.0
Classifier: License :: OSI Approved :: MIT License
Classifier: Programming Language :: Python :: 3
Classifier: Programming Language :: Python :: 3.9
Classifier: Programming Language :: Python :: 3.10
Classifier: Programming Language :: Python :: 3.11
Classifier: Programming Language :: Python :: 3.12
Classifier: Programming Language :: Python :: 3.13
Classifier: Programming Language :: Python :: 3.14
Requires-Dist: numpy (>=1.26.4,<3.0.0)
Requires-Dist: pyparsing (>=3.0.0,<4.0.0)
Project-URL: Homepage, https://github.com/dmitry-lesnik/vector-logic
Project-URL: Repository, https://github.com/dmitry-lesnik/vector-logic
